llm7_validator/__init__.py
llm7_validator-2025.6.110528.dist-info/licenses/LICENSE
llm7_validator-2025.6.110528.dist-info/METADATA
llm7_validator-2025.6.110528.dist-info/WHEEL
llm7_validator-2025.6.110528.dist-info/top_level.txt
llm7_validator-2025.6.110528.dist-info/RECORD
