Metadata-Version: 2.4
Name: llm7-validator
Version: 2025.6.110528
Summary: Validator for LLM7 chat completion requests with Pydantic and model ID constraints.
Home-page: https://github.com/chigwell/llm7-validator
Author: Eugene Evstafev
Author-email: support@llm7.io
License: MIT
Classifier: License :: OSI Approved :: MIT License
Classifier: Development Status :: 3 - Alpha
Classifier: Intended Audience :: Developers
Classifier: Programming Language :: Python :: 3
Classifier: Programming Language :: Python :: 3.10
Classifier: Operating System :: OS Independent
Requires-Python: >=3.10
License-File: LICENSE
Requires-Dist: requests-cache==1.2.1
Requires-Dist: pydantic==2.11.5
Requires-Dist: typing==3.7.4.3
Dynamic: author
Dynamic: author-email
Dynamic: classifier
Dynamic: description
Dynamic: description-content-type
Dynamic: home-page
Dynamic: license
Dynamic: license-file
Dynamic: requires-dist
Dynamic: requires-python
Dynamic: summary
